semantic_version_splunk_test/__init__.py
semantic_version_splunk_test/base.py
semantic_version_splunk_test/compat.py
semantic_version_splunk_test/django_fields.py
semantic_version_splunk_test-2.6.0.dist-info/LICENSE
semantic_version_splunk_test-2.6.0.dist-info/METADATA
semantic_version_splunk_test-2.6.0.dist-info/WHEEL
semantic_version_splunk_test-2.6.0.dist-info/top_level.txt
semantic_version_splunk_test-2.6.0.dist-info/RECORD
