Metadata-Version: 2.1
Name: semantic-version-splunk-test
Version: 2.6.0
Summary: A library implementing the 'SemVer' scheme.
Home-page: https://github.com/rbarrois/python-semanticversion
Download-URL: http://pypi.python.org/pypi/semantic_version/
Author: Raphaël Barrois
Author-email: raphael.barrois+semver@polytechnique.org
License: BSD
Keywords: semantic version,versioning,version
Classifier: Development Status :: 5 - Production/Stable
Classifier: Intended Audience :: Developers
Classifier: License :: OSI Approved :: BSD License
Classifier: Topic :: Software Development :: Libraries :: Python Modules
Classifier: Operating System :: OS Independent
Classifier: Programming Language :: Python
Classifier: Programming Language :: Python :: 2
Classifier: Programming Language :: Python :: 2.7
Classifier: Programming Language :: Python :: 3
Classifier: Programming Language :: Python :: 3.4
Classifier: Programming Language :: Python :: 3.5
Classifier: Topic :: Software Development :: Libraries :: Python Modules
License-File: LICENSE
